[{"stock_code":"600426","stock_name":"华鲁恒升","fund_code":"000471","fund_name":"富国城镇发展","ratio":"4.05%","count":"129.57","money":"3574.76"},{"stock_code":"601567","stock_name":"三星医疗","fund_code":"000471","fund_name":"富国城镇发展","ratio":"3.92%","count":"168.89","money":"3462.25"},{"stock_code":"601985","stock_name":"中国核电","fund_code":"000471","fund_name":"富国城镇发展","ratio":"3.66%","count":"430.75","money":"3230.63"},{"stock_code":"002851","stock_name":"麦格米特","fund_code":"000471","fund_name":"富国城镇发展","ratio":"3.28%","count":"117.86","money":"2899.36"},{"stock_code":"300760","stock_name":"迈瑞医疗","fund_code":"000471","fund_name":"富国城镇发展","ratio":"3.08%","count":"9.35","money":"2717.11"},{"stock_code":"002223","stock_name":"鱼跃医疗","fund_code":"000471","fund_name":"富国城镇发展","ratio":"2.88%","count":"73.57","money":"2544.05"},{"stock_code":"002475","stock_name":"立讯精密","fund_code":"000471","fund_name":"富国城镇发展","ratio":"2.86%","count":"73.38","money":"2527.97"},{"stock_code":"002444","stock_name":"巨星科技","fund_code":"000471","fund_name":"富国城镇发展","ratio":"2.81%","count":"110.03","money":"2477.88"},{"stock_code":"300482","stock_name":"万孚生物","fund_code":"000471","fund_name":"富国城镇发展","ratio":"2.80%","count":"81.84","money":"2469.11"},{"stock_code":"603277","stock_name":"银都股份","fund_code":"000471","fund_name":"富国城镇发展","ratio":"2.68%","count":"88.27","money":"2367.40"},{"stock_code":"600422","stock_name":"昆药集团","fund_code":"000471","fund_name":"富国城镇发展","ratio":"2.53%","count":"107.18","money":"2235.77"},{"stock_code":"601000","stock_name":"唐山港","fund_code":"000471","fund_name":"富国城镇发展","ratio":"2.48%","count":"624.67","money":"2186.35"},{"stock_code":"600519","stock_name":"贵州茅台","fund_code":"000471","fund_name":"富国城镇发展","ratio":"2.42%","count":"1.24","money":"2140.24"},{"stock_code":"000333","stock_name":"美的集团","fund_code":"000471","fund_name":"富国城镇发展","ratio":"2.19%","count":"35.46","money":"1937.31"},{"stock_code":"000061","stock_name":"农产品","fund_code":"000471","fund_name":"富国城镇发展","ratio":"2.03%","count":"277.15","money":"1793.15"},{"stock_code":"600941","stock_name":"中国移动","fund_code":"000471","fund_name":"富国城镇发展","ratio":"1.94%","count":"17.25","money":"1716.07"},{"stock_code":"002332","stock_name":"仙琚制药","fund_code":"000471","fund_name":"富国城镇发展","ratio":"1.90%","count":"131.50","money":"1679.26"},{"stock_code":"300677","stock_name":"英科医疗","fund_code":"000471","fund_name":"富国城镇发展","ratio":"1.88%","count":"71.09","money":"1660.77"},{"stock_code":"002044","stock_name":"美年健康","fund_code":"000471","fund_name":"富国城镇发展","ratio":"1.79%","count":"262.43","money":"1577.20"},{"stock_code":"603855","stock_name":"华荣股份","fund_code":"000471","fund_name":"富国城镇发展","ratio":"1.78%","count":"78.55","money":"1567.93"},{"stock_code":"603259","stock_name":"药明康德","fund_code":"000471","fund_name":"富国城镇发展","ratio":"1.64%","count":"19.95","money":"1451.70"},{"stock_code":"002028","stock_name":"思源电气","fund_code":"000471","fund_name":"富国城镇发展","ratio":"1.59%","count":"26.95","money":"1402.48"},{"stock_code":"603901","stock_name":"永创智能","fund_code":"000471","fund_name":"富国城镇发展","ratio":"1.55%","count":"115.29","money":"1371.95"},{"stock_code":"603556","stock_name":"海兴电力","fund_code":"000471","fund_name":"富国城镇发展","ratio":"1.50%","count":"45.65","money":"1325.10"},{"stock_code":"300910","stock_name":"瑞丰新材","fund_code":"000471","fund_name":"富国城镇发展","ratio":"1.50%","count":"28.78","money":"1322.15"},{"stock_code":"002960","stock_name":"青鸟消防","fund_code":"000471","fund_name":"富国城镇发展","ratio":"1.49%","count":"95.33","money":"1319.42"},{"stock_code":"601677","stock_name":"明泰铝业","fund_code":"000471","fund_name":"富国城镇发展","ratio":"1.47%","count":"114.41","money":"1297.42"},{"stock_code":"600406","stock_name":"国电南瑞","fund_code":"000471","fund_name":"富国城镇发展","ratio":"1.43%","count":"56.54","money":"1262.04"},{"stock_code":"603987","stock_name":"康德莱","fund_code":"000471","fund_name":"富国城镇发展","ratio":"1.26%","count":"116.61","money":"1112.44"},{"stock_code":"001914","stock_name":"招商积余","fund_code":"000471","fund_name":"富国城镇发展","ratio":"1.26%","count":"92.98","money":"1112.00"}]