[{"stock_code":"688041","stock_name":"海光信息","fund_code":"001072","fund_name":"华安智能装备","ratio":"6.47%","count":"95.09","money":"6749.29"},{"stock_code":"688072","stock_name":"拓荆科技","fund_code":"001072","fund_name":"华安智能装备","ratio":"4.55%","count":"20.50","money":"4742.67"},{"stock_code":"002156","stock_name":"通富微电","fund_code":"001072","fund_name":"华安智能装备","ratio":"3.83%","count":"172.78","money":"3994.67"},{"stock_code":"688036","stock_name":"传音控股","fund_code":"001072","fund_name":"华安智能装备","ratio":"3.68%","count":"27.72","money":"3836.72"},{"stock_code":"000977","stock_name":"浪潮信息","fund_code":"001072","fund_name":"华安智能装备","ratio":"3.61%","count":"113.29","money":"3761.23"},{"stock_code":"688256","stock_name":"寒武纪","fund_code":"001072","fund_name":"华安智能装备","ratio":"3.05%","count":"23.60","money":"3184.85"},{"stock_code":"688502","stock_name":"茂莱光学","fund_code":"001072","fund_name":"华安智能装备","ratio":"2.94%","count":"14.10","money":"3060.17"},{"stock_code":"300782","stock_name":"卓胜微","fund_code":"001072","fund_name":"华安智能装备","ratio":"2.91%","count":"21.55","money":"3038.03"},{"stock_code":"300456","stock_name":"赛微电子","fund_code":"001072","fund_name":"华安智能装备","ratio":"2.58%","count":"111.93","money":"2690.80"},{"stock_code":"002150","stock_name":"通润装备","fund_code":"001072","fund_name":"华安智能装备","ratio":"2.46%","count":"144.63","money":"2565.74"},{"stock_code":"600536","stock_name":"中国软件","fund_code":"001072","fund_name":"华安智能装备","ratio":"2.33%","count":"67.12","money":"2433.81"},{"stock_code":"688008","stock_name":"澜起科技","fund_code":"001072","fund_name":"华安智能装备","ratio":"2.33%","count":"41.40","money":"2432.75"},{"stock_code":"002371","stock_name":"北方华创","fund_code":"001072","fund_name":"华安智能装备","ratio":"2.24%","count":"9.52","money":"2339.16"},{"stock_code":"688120","stock_name":"华海清科","fund_code":"001072","fund_name":"华安智能装备","ratio":"2.18%","count":"12.12","money":"2274.23"},{"stock_code":"688478","stock_name":"晶升股份","fund_code":"001072","fund_name":"华安智能装备","ratio":"2.17%","count":"43.46","money":"2259.66"},{"stock_code":"688220","stock_name":"翱捷科技","fund_code":"001072","fund_name":"华安智能装备","ratio":"2.10%","count":"31.03","money":"2185.76"},{"stock_code":"688286","stock_name":"敏芯股份","fund_code":"001072","fund_name":"华安智能装备","ratio":"2.03%","count":"29.46","money":"2112.35"},{"stock_code":"688475","stock_name":"萤石网络","fund_code":"001072","fund_name":"华安智能装备","ratio":"1.99%","count":"46.20","money":"2074.51"},{"stock_code":"688301","stock_name":"奕瑞科技","fund_code":"001072","fund_name":"华安智能装备","ratio":"1.92%","count":"6.16","money":"2003.60"},{"stock_code":"300394","stock_name":"天孚通信","fund_code":"001072","fund_name":"华安智能装备","ratio":"1.89%","count":"21.53","money":"1970.43"},{"stock_code":"688496","stock_name":"清越科技","fund_code":"001072","fund_name":"华安智能装备","ratio":"1.74%","count":"81.21","money":"1818.36"},{"stock_code":"688486","stock_name":"龙迅股份","fund_code":"001072","fund_name":"华安智能装备","ratio":"1.73%","count":"15.16","money":"1800.54"},{"stock_code":"000063","stock_name":"中兴通讯","fund_code":"001072","fund_name":"华安智能装备","ratio":"1.70%","count":"66.75","money":"1767.54"},{"stock_code":"002236","stock_name":"大华股份","fund_code":"001072","fund_name":"华安智能装备","ratio":"1.64%","count":"92.46","money":"1705.85"},{"stock_code":"000938","stock_name":"紫光股份","fund_code":"001072","fund_name":"华安智能装备","ratio":"1.57%","count":"84.45","money":"1634.11"},{"stock_code":"300037","stock_name":"新宙邦","fund_code":"001072","fund_name":"华安智能装备","ratio":"1.52%","count":"33.40","money":"1579.82"},{"stock_code":"300001","stock_name":"特锐德","fund_code":"001072","fund_name":"华安智能装备","ratio":"1.43%","count":"74.02","money":"1487.80"},{"stock_code":"603595","stock_name":"东尼电子","fund_code":"001072","fund_name":"华安智能装备","ratio":"1.33%","count":"37.72","money":"1387.72"},{"stock_code":"688608","stock_name":"恒玄科技","fund_code":"001072","fund_name":"华安智能装备","ratio":"1.28%","count":"8.68","money":"1338.37"},{"stock_code":"688498","stock_name":"源杰科技","fund_code":"001072","fund_name":"华安智能装备","ratio":"1.25%","count":"8.73","money":"1301.10"}]