[{"stock_code":"600079","stock_name":"人福医药","fund_code":"002264","fund_name":"华夏乐享健康","ratio":"8.06%","count":"180.99","money":"4499.39"},{"stock_code":"000963","stock_name":"华东医药","fund_code":"002264","fund_name":"华夏乐享健康","ratio":"6.68%","count":"89.94","money":"3729.07"},{"stock_code":"600276","stock_name":"恒瑞医药","fund_code":"002264","fund_name":"华夏乐享健康","ratio":"5.60%","count":"69.07","money":"3124.18"},{"stock_code":"002422","stock_name":"科伦药业","fund_code":"002264","fund_name":"华夏乐享健康","ratio":"4.85%","count":"93.14","money":"2705.72"},{"stock_code":"000403","stock_name":"派林生物","fund_code":"002264","fund_name":"华夏乐享健康","ratio":"4.20%","count":"86.08","money":"2344.82"},{"stock_code":"300765","stock_name":"新诺威","fund_code":"002264","fund_name":"华夏乐享健康","ratio":"3.55%","count":"54.15","money":"1982.87"},{"stock_code":"600129","stock_name":"太极集团","fund_code":"002264","fund_name":"华夏乐享健康","ratio":"3.42%","count":"41.09","money":"1909.05"},{"stock_code":"300760","stock_name":"迈瑞医疗","fund_code":"002264","fund_name":"华夏乐享健康","ratio":"3.25%","count":"6.24","money":"1813.14"},{"stock_code":"002675","stock_name":"东诚药业","fund_code":"002264","fund_name":"华夏乐享健康","ratio":"3.24%","count":"98.75","money":"1810.09"},{"stock_code":"600161","stock_name":"天坛生物","fund_code":"002264","fund_name":"华夏乐享健康","ratio":"3.09%","count":"55.72","money":"1724.02"},{"stock_code":"300015","stock_name":"爱尔眼科","fund_code":"002264","fund_name":"华夏乐享健康","ratio":"2.85%","count":"100.54","money":"1590.55"},{"stock_code":"600511","stock_name":"国药股份","fund_code":"002264","fund_name":"华夏乐享健康","ratio":"2.79%","count":"54.36","money":"1555.78"},{"stock_code":"300122","stock_name":"智飞生物","fund_code":"002264","fund_name":"华夏乐享健康","ratio":"2.69%","count":"24.59","money":"1502.93"},{"stock_code":"301239","stock_name":"普瑞眼科","fund_code":"002264","fund_name":"华夏乐享健康","ratio":"2.56%","count":"16.60","money":"1427.44"},{"stock_code":"600211","stock_name":"西藏药业","fund_code":"002264","fund_name":"华夏乐享健康","ratio":"2.36%","count":"26.98","money":"1316.62"},{"stock_code":"600062","stock_name":"华润双鹤","fund_code":"002264","fund_name":"华夏乐享健康","ratio":"1.81%","count":"54.30","money":"1009.98"},{"stock_code":"603309","stock_name":"维力医疗","fund_code":"002264","fund_name":"华夏乐享健康","ratio":"1.78%","count":"69.73","money":"992.19"},{"stock_code":"002332","stock_name":"仙琚制药","fund_code":"002264","fund_name":"华夏乐享健康","ratio":"1.71%","count":"74.91","money":"956.60"},{"stock_code":"300314","stock_name":"戴维医疗","fund_code":"002264","fund_name":"华夏乐享健康","ratio":"1.67%","count":"61.74","money":"934.74"},{"stock_code":"688331","stock_name":"荣昌生物","fund_code":"002264","fund_name":"华夏乐享健康","ratio":"1.59%","count":"14.31","money":"888.28"},{"stock_code":"688016","stock_name":"心脉医疗","fund_code":"002264","fund_name":"华夏乐享健康","ratio":"1.53%","count":"4.40","money":"855.73"},{"stock_code":"600976","stock_name":"健民集团","fund_code":"002264","fund_name":"华夏乐享健康","ratio":"1.48%","count":"12.69","money":"828.02"},{"stock_code":"000423","stock_name":"东阿阿胶","fund_code":"002264","fund_name":"华夏乐享健康","ratio":"1.22%","count":"13.83","money":"682.02"},{"stock_code":"688253","stock_name":"英诺特","fund_code":"002264","fund_name":"华夏乐享健康","ratio":"1.17%","count":"26.11","money":"653.05"},{"stock_code":"300181","stock_name":"佐力药业","fund_code":"002264","fund_name":"华夏乐享健康","ratio":"1.10%","count":"57.81","money":"616.25"},{"stock_code":"002432","stock_name":"九安医疗","fund_code":"002264","fund_name":"华夏乐享健康","ratio":"1.10%","count":"16.33","money":"615.15"},{"stock_code":"688581","stock_name":"安杰思","fund_code":"002264","fund_name":"华夏乐享健康","ratio":"1.04%","count":"4.66","money":"581.50"},{"stock_code":"600420","stock_name":"国药现代","fund_code":"002264","fund_name":"华夏乐享健康","ratio":"1.03%","count":"58.50","money":"572.72"},{"stock_code":"603707","stock_name":"健友股份","fund_code":"002264","fund_name":"华夏乐享健康","ratio":"0.99%","count":"37.04","money":"555.57"},{"stock_code":"600587","stock_name":"新华医疗","fund_code":"002264","fund_name":"华夏乐享健康","ratio":"0.95%","count":"20.55","money":"529.98"}]