[{"stock_code":"300308","stock_name":"中际旭创","fund_code":"006888","fund_name":"诺德新生活混","ratio":"4.14%","count":"27.39","money":"3092.21"},{"stock_code":"300502","stock_name":"新易盛","fund_code":"006888","fund_name":"诺德新生活混","ratio":"4.01%","count":"60.73","money":"2995.22"},{"stock_code":"300394","stock_name":"天孚通信","fund_code":"006888","fund_name":"诺德新生活混","ratio":"3.98%","count":"32.51","money":"2975.55"},{"stock_code":"300033","stock_name":"同花顺","fund_code":"006888","fund_name":"诺德新生活混","ratio":"2.86%","count":"13.62","money":"2137.26"},{"stock_code":"605289","stock_name":"罗曼股份","fund_code":"006888","fund_name":"诺德新生活混","ratio":"2.82%","count":"36.66","money":"2108.16"},{"stock_code":"300130","stock_name":"新国都","fund_code":"006888","fund_name":"诺德新生活混","ratio":"2.79%","count":"86.31","money":"2088.74"},{"stock_code":"002315","stock_name":"焦点科技","fund_code":"006888","fund_name":"诺德新生活混","ratio":"2.71%","count":"61.07","money":"2023.32"},{"stock_code":"300002","stock_name":"神州泰岳","fund_code":"006888","fund_name":"诺德新生活混","ratio":"2.69%","count":"227.12","money":"2010.01"},{"stock_code":"601138","stock_name":"工业富联","fund_code":"006888","fund_name":"诺德新生活混","ratio":"2.67%","count":"132.26","money":"1999.76"},{"stock_code":"688012","stock_name":"中微公司","fund_code":"006888","fund_name":"诺德新生活混","ratio":"2.65%","count":"12.92","money":"1984.40"},{"stock_code":"300624","stock_name":"万兴科技","fund_code":"006888","fund_name":"诺德新生活混","ratio":"2.53%","count":"20.01","money":"1893.34"},{"stock_code":"300570","stock_name":"太辰光","fund_code":"006888","fund_name":"诺德新生活混","ratio":"2.52%","count":"48.30","money":"1886.08"},{"stock_code":"002475","stock_name":"立讯精密","fund_code":"006888","fund_name":"诺德新生活混","ratio":"2.49%","count":"54.14","money":"1865.12"},{"stock_code":"300045","stock_name":"华力创通","fund_code":"006888","fund_name":"诺德新生活混","ratio":"2.49%","count":"76.63","money":"1864.41"},{"stock_code":"688498","stock_name":"源杰科技","fund_code":"006888","fund_name":"诺德新生活混","ratio":"2.40%","count":"12.04","money":"1793.63"},{"stock_code":"601595","stock_name":"上海电影","fund_code":"006888","fund_name":"诺德新生活混","ratio":"2.38%","count":"68.96","money":"1781.30"},{"stock_code":"688328","stock_name":"深科达","fund_code":"006888","fund_name":"诺德新生活混","ratio":"2.22%","count":"37.04","money":"1661.36"},{"stock_code":"002292","stock_name":"奥飞娱乐","fund_code":"006888","fund_name":"诺德新生活混","ratio":"2.15%","count":"183.64","money":"1606.87"},{"stock_code":"603496","stock_name":"恒为科技","fund_code":"006888","fund_name":"诺德新生活混","ratio":"2.04%","count":"48.92","money":"1524.35"},{"stock_code":"002920","stock_name":"德赛西威","fund_code":"006888","fund_name":"诺德新生活混","ratio":"2.01%","count":"11.63","money":"1506.20"},{"stock_code":"300418","stock_name":"昆仑万维","fund_code":"006888","fund_name":"诺德新生活混","ratio":"2.00%","count":"39.92","money":"1493.01"},{"stock_code":"688072","stock_name":"拓荆科技","fund_code":"006888","fund_name":"诺德新生活混","ratio":"1.89%","count":"6.10","money":"1411.05"},{"stock_code":"601799","stock_name":"星宇股份","fund_code":"006888","fund_name":"诺德新生活混","ratio":"1.88%","count":"10.74","money":"1408.12"},{"stock_code":"300494","stock_name":"盛天网络","fund_code":"006888","fund_name":"诺德新生活混","ratio":"1.86%","count":"87.88","money":"1389.38"},{"stock_code":"300556","stock_name":"丝路视觉","fund_code":"006888","fund_name":"诺德新生活混","ratio":"1.68%","count":"34.11","money":"1256.91"},{"stock_code":"003021","stock_name":"兆威机电","fund_code":"006888","fund_name":"诺德新生活混","ratio":"1.66%","count":"13.18","money":"1238.79"},{"stock_code":"300757","stock_name":"罗博特科","fund_code":"006888","fund_name":"诺德新生活混","ratio":"1.62%","count":"14.88","money":"1211.16"},{"stock_code":"688609","stock_name":"九联科技","fund_code":"006888","fund_name":"诺德新生活混","ratio":"1.52%","count":"86.03","money":"1135.58"},{"stock_code":"002517","stock_name":"恺英网络","fund_code":"006888","fund_name":"诺德新生活混","ratio":"1.52%","count":"101.64","money":"1135.33"},{"stock_code":"603722","stock_name":"阿科力","fund_code":"006888","fund_name":"诺德新生活混","ratio":"1.51%","count":"20.94","money":"1128.67"}]