[{"stock_code":"601899","stock_name":"紫金矿业","fund_code":"011428","fund_name":"广发价值驱动","ratio":"9.75%","count":"313.15","money":"3901.85"},{"stock_code":"000333","stock_name":"美的集团","fund_code":"011428","fund_name":"广发价值驱动","ratio":"8.61%","count":"63.03","money":"3443.33"},{"stock_code":"002415","stock_name":"海康威视","fund_code":"011428","fund_name":"广发价值驱动","ratio":"8.04%","count":"92.62","money":"3215.77"},{"stock_code":"002003","stock_name":"伟星股份","fund_code":"011428","fund_name":"广发价值驱动","ratio":"7.95%","count":"293.12","money":"3180.38"},{"stock_code":"002832","stock_name":"比音勒芬","fund_code":"011428","fund_name":"广发价值驱动","ratio":"7.34%","count":"92.67","money":"2937.52"},{"stock_code":"600309","stock_name":"万华化学","fund_code":"011428","fund_name":"广发价值驱动","ratio":"7.13%","count":"37.12","money":"2851.40"},{"stock_code":"603997","stock_name":"继峰股份","fund_code":"011428","fund_name":"广发价值驱动","ratio":"6.84%","count":"203.26","money":"2737.91"},{"stock_code":"603730","stock_name":"岱美股份","fund_code":"011428","fund_name":"广发价值驱动","ratio":"6.76%","count":"186.69","money":"2705.14"},{"stock_code":"603833","stock_name":"欧派家居","fund_code":"011428","fund_name":"广发价值驱动","ratio":"6.58%","count":"37.82","money":"2632.65"},{"stock_code":"002557","stock_name":"洽洽食品","fund_code":"011428","fund_name":"广发价值驱动","ratio":"5.74%","count":"65.99","money":"2297.77"},{"stock_code":"000589","stock_name":"贵州轮胎","fund_code":"011428","fund_name":"广发价值驱动","ratio":"3.16%","count":"206.31","money":"1262.62"},{"stock_code":"603300","stock_name":"华铁应急","fund_code":"011428","fund_name":"广发价值驱动","ratio":"3.11%","count":"194.59","money":"1245.36"},{"stock_code":"601677","stock_name":"明泰铝业","fund_code":"011428","fund_name":"广发价值驱动","ratio":"2.80%","count":"98.68","money":"1119.03"},{"stock_code":"300575","stock_name":"中旗股份","fund_code":"011428","fund_name":"广发价值驱动","ratio":"2.73%","count":"142.96","money":"1092.24"},{"stock_code":"002541","stock_name":"鸿路钢构","fund_code":"011428","fund_name":"广发价值驱动","ratio":"2.47%","count":"45.44","money":"987.41"},{"stock_code":"600933","stock_name":"爱柯迪","fund_code":"011428","fund_name":"广发价值驱动","ratio":"2.24%","count":"40.81","money":"895.37"},{"stock_code":"002027","stock_name":"分众传媒","fund_code":"011428","fund_name":"广发价值驱动","ratio":"2.03%","count":"128.23","money":"810.41"},{"stock_code":"002318","stock_name":"久立特材","fund_code":"011428","fund_name":"广发价值驱动","ratio":"1.50%","count":"30.28","money":"601.97"}]