[{"stock_code":"601881","stock_name":"中国银河","fund_code":"013742","fund_name":"兴业聚源混合","ratio":"2.55%","count":"16.00","money":"192.80"},{"stock_code":"600900","stock_name":"长江电力","fund_code":"013742","fund_name":"兴业聚源混合","ratio":"2.47%","count":"8.00","money":"186.72"},{"stock_code":"601288","stock_name":"农业银行","fund_code":"013742","fund_name":"兴业聚源混合","ratio":"2.41%","count":"50.00","money":"182.00"},{"stock_code":"601857","stock_name":"中国石油","fund_code":"013742","fund_name":"兴业聚源混合","ratio":"2.33%","count":"25.00","money":"176.50"},{"stock_code":"002475","stock_name":"立讯精密","fund_code":"013742","fund_name":"兴业聚源混合","ratio":"2.28%","count":"5.00","money":"172.25"},{"stock_code":"300674","stock_name":"宇信科技","fund_code":"013742","fund_name":"兴业聚源混合","ratio":"1.51%","count":"7.00","money":"113.96"},{"stock_code":"000333","stock_name":"美的集团","fund_code":"013742","fund_name":"兴业聚源混合","ratio":"1.44%","count":"2.00","money":"109.26"},{"stock_code":"600350","stock_name":"山东高速","fund_code":"013742","fund_name":"兴业聚源混合","ratio":"1.38%","count":"15.00","money":"104.10"},{"stock_code":"601985","stock_name":"中国核电","fund_code":"013742","fund_name":"兴业聚源混合","ratio":"1.29%","count":"13.00","money":"97.50"},{"stock_code":"688099","stock_name":"晶晨股份","fund_code":"013742","fund_name":"兴业聚源混合","ratio":"1.23%","count":"1.48","money":"92.69"},{"stock_code":"002050","stock_name":"三花智控","fund_code":"013742","fund_name":"兴业聚源混合","ratio":"1.17%","count":"3.00","money":"88.20"},{"stock_code":"300003","stock_name":"乐普医疗","fund_code":"013742","fund_name":"兴业聚源混合","ratio":"1.11%","count":"5.20","money":"84.03"},{"stock_code":"002273","stock_name":"水晶光电","fund_code":"013742","fund_name":"兴业聚源混合","ratio":"1.07%","count":"6.00","money":"81.24"},{"stock_code":"601233","stock_name":"桐昆股份","fund_code":"013742","fund_name":"兴业聚源混合","ratio":"1.00%","count":"5.00","money":"75.65"},{"stock_code":"600522","stock_name":"中天科技","fund_code":"013742","fund_name":"兴业聚源混合","ratio":"0.99%","count":"6.00","money":"74.94"},{"stock_code":"601689","stock_name":"拓普集团","fund_code":"013742","fund_name":"兴业聚源混合","ratio":"0.97%","count":"1.00","money":"73.50"},{"stock_code":"688390","stock_name":"固德威","fund_code":"013742","fund_name":"兴业聚源混合","ratio":"0.86%","count":"0.50","money":"65.29"},{"stock_code":"688981","stock_name":"中芯国际","fund_code":"013742","fund_name":"兴业聚源混合","ratio":"0.84%","count":"1.20","money":"63.62"},{"stock_code":"601088","stock_name":"中国神华","fund_code":"013742","fund_name":"兴业聚源混合","ratio":"0.83%","count":"2.00","money":"62.70"},{"stock_code":"002594","stock_name":"比亚迪","fund_code":"013742","fund_name":"兴业聚源混合","ratio":"0.79%","count":"0.30","money":"59.40"},{"stock_code":"300031","stock_name":"宝通科技","fund_code":"013742","fund_name":"兴业聚源混合","ratio":"0.74%","count":"3.00","money":"55.62"},{"stock_code":"601899","stock_name":"紫金矿业","fund_code":"013742","fund_name":"兴业聚源混合","ratio":"0.66%","count":"4.00","money":"49.84"},{"stock_code":"600745","stock_name":"闻泰科技","fund_code":"013742","fund_name":"兴业聚源混合","ratio":"0.56%","count":"1.00","money":"42.31"},{"stock_code":"002472","stock_name":"双环传动","fund_code":"013742","fund_name":"兴业聚源混合","ratio":"0.34%","count":"1.00","money":"26.02"}]