[{"stock_code":"000568","stock_name":"泸州老窖","fund_code":"015346","fund_name":"摩根健康品质","ratio":"9.62%","count":"81.48","money":"14618.87"},{"stock_code":"603477","stock_name":"巨星农牧","fund_code":"015346","fund_name":"摩根健康品质","ratio":"9.57%","count":"388.46","money":"14555.66"},{"stock_code":"000858","stock_name":"五粮液","fund_code":"015346","fund_name":"摩根健康品质","ratio":"9.56%","count":"103.59","money":"14534.75"},{"stock_code":"002840","stock_name":"华统股份","fund_code":"015346","fund_name":"摩根健康品质","ratio":"9.53%","count":"696.51","money":"14480.42"},{"stock_code":"002567","stock_name":"唐人神","fund_code":"015346","fund_name":"摩根健康品质","ratio":"9.23%","count":"1,869.92","money":"14024.39"},{"stock_code":"600779","stock_name":"水井坊","fund_code":"015346","fund_name":"摩根健康品质","ratio":"9.21%","count":"238.35","money":"14007.97"},{"stock_code":"002100","stock_name":"天康生物","fund_code":"015346","fund_name":"摩根健康品质","ratio":"9.17%","count":"1,588.87","money":"13934.37"},{"stock_code":"600519","stock_name":"贵州茅台","fund_code":"015346","fund_name":"摩根健康品质","ratio":"8.03%","count":"7.07","money":"12204.72"},{"stock_code":"600975","stock_name":"新五丰","fund_code":"015346","fund_name":"摩根健康品质","ratio":"7.89%","count":"1,148.51","money":"12001.97"},{"stock_code":"002714","stock_name":"牧原股份","fund_code":"015346","fund_name":"摩根健康品质","ratio":"7.53%","count":"277.81","money":"11440.14"},{"stock_code":"300498","stock_name":"温氏股份","fund_code":"015346","fund_name":"摩根健康品质","ratio":"4.75%","count":"360.34","money":"7228.37"}]