[{"stock_code":"300416","stock_name":"苏试试验","fund_code":"519026","fund_name":"海富通中小盘","ratio":"9.33%","count":"233.13","money":"4282.55"},{"stock_code":"688596","stock_name":"正帆科技","fund_code":"519026","fund_name":"海富通中小盘","ratio":"6.48%","count":"75.06","money":"2974.51"},{"stock_code":"002947","stock_name":"恒铭达","fund_code":"519026","fund_name":"海富通中小盘","ratio":"5.33%","count":"76.02","money":"2446.21"},{"stock_code":"603650","stock_name":"彤程新材","fund_code":"519026","fund_name":"海富通中小盘","ratio":"5.14%","count":"70.83","money":"2358.64"},{"stock_code":"301095","stock_name":"广立微","fund_code":"519026","fund_name":"海富通中小盘","ratio":"4.99%","count":"30.65","money":"2290.46"},{"stock_code":"000988","stock_name":"华工科技","fund_code":"519026","fund_name":"海富通中小盘","ratio":"4.75%","count":"73.29","money":"2181.11"},{"stock_code":"002465","stock_name":"海格通信","fund_code":"519026","fund_name":"海富通中小盘","ratio":"4.66%","count":"166.35","money":"2137.60"},{"stock_code":"688208","stock_name":"道通科技","fund_code":"519026","fund_name":"海富通中小盘","ratio":"4.01%","count":"77.53","money":"1841.34"},{"stock_code":"688311","stock_name":"盟升电子","fund_code":"519026","fund_name":"海富通中小盘","ratio":"3.97%","count":"35.71","money":"1821.55"},{"stock_code":"301052","stock_name":"果麦文化","fund_code":"519026","fund_name":"海富通中小盘","ratio":"3.74%","count":"39.23","money":"1717.49"},{"stock_code":"300570","stock_name":"太辰光","fund_code":"519026","fund_name":"海富通中小盘","ratio":"3.49%","count":"41.07","money":"1603.86"},{"stock_code":"605168","stock_name":"三人行","fund_code":"519026","fund_name":"海富通中小盘","ratio":"3.45%","count":"25.02","money":"1585.27"},{"stock_code":"300559","stock_name":"佳发教育","fund_code":"519026","fund_name":"海富通中小盘","ratio":"3.11%","count":"92.28","money":"1430.34"},{"stock_code":"300502","stock_name":"新易盛","fund_code":"519026","fund_name":"海富通中小盘","ratio":"3.04%","count":"28.31","money":"1396.25"},{"stock_code":"000810","stock_name":"创维数字","fund_code":"519026","fund_name":"海富通中小盘","ratio":"2.63%","count":"76.86","money":"1207.47"},{"stock_code":"688685","stock_name":"迈信林","fund_code":"519026","fund_name":"海富通中小盘","ratio":"2.60%","count":"40.17","money":"1193.93"},{"stock_code":"603062","stock_name":"麦加芯彩","fund_code":"519026","fund_name":"海富通中小盘","ratio":"2.50%","count":"18.41","money":"1149.54"},{"stock_code":"300115","stock_name":"长盈精密","fund_code":"519026","fund_name":"海富通中小盘","ratio":"2.32%","count":"80.46","money":"1066.10"},{"stock_code":"300568","stock_name":"星源材质","fund_code":"519026","fund_name":"海富通中小盘","ratio":"2.30%","count":"68.40","money":"1054.73"},{"stock_code":"300762","stock_name":"上海瀚讯","fund_code":"519026","fund_name":"海富通中小盘","ratio":"2.19%","count":"66.79","money":"1007.19"},{"stock_code":"688772","stock_name":"珠海冠宇","fund_code":"519026","fund_name":"海富通中小盘","ratio":"1.67%","count":"34.85","money":"767.01"},{"stock_code":"600765","stock_name":"中航重机","fund_code":"519026","fund_name":"海富通中小盘","ratio":"1.48%","count":"35.53","money":"678.98"},{"stock_code":"603986","stock_name":"兆易创新","fund_code":"519026","fund_name":"海富通中小盘","ratio":"1.47%","count":"7.33","money":"677.22"},{"stock_code":"603888","stock_name":"新华网","fund_code":"519026","fund_name":"海富通中小盘","ratio":"1.40%","count":"25.51","money":"642.60"},{"stock_code":"002463","stock_name":"沪电股份","fund_code":"519026","fund_name":"海富通中小盘","ratio":"1.30%","count":"26.93","money":"595.69"},{"stock_code":"300182","stock_name":"捷成股份","fund_code":"519026","fund_name":"海富通中小盘","ratio":"1.25%","count":"113.42","money":"576.17"},{"stock_code":"300806","stock_name":"斯迪克","fund_code":"519026","fund_name":"海富通中小盘","ratio":"1.05%","count":"34.16","money":"480.63"},{"stock_code":"002414","stock_name":"高德红外","fund_code":"519026","fund_name":"海富通中小盘","ratio":"1.03%","count":"64.55","money":"471.22"},{"stock_code":"002600","stock_name":"领益智造","fund_code":"519026","fund_name":"海富通中小盘","ratio":"1.00%","count":"67.63","money":"457.18"},{"stock_code":"300017","stock_name":"网宿科技","fund_code":"519026","fund_name":"海富通中小盘","ratio":"0.83%","count":"48.41","money":"380.02"}]