[{"stock_code":"603566","stock_name":"普莱柯","fund_code":"970033","fund_name":"东海海睿进取","ratio":"8.86%","count":"32.92","money":"745.64"},{"stock_code":"300760","stock_name":"迈瑞医疗","fund_code":"970033","fund_name":"东海海睿进取","ratio":"8.25%","count":"2.39","money":"694.53"},{"stock_code":"300498","stock_name":"温氏股份","fund_code":"970033","fund_name":"东海海睿进取","ratio":"7.36%","count":"30.87","money":"619.25"},{"stock_code":"300783","stock_name":"三只松鼠","fund_code":"970033","fund_name":"东海海睿进取","ratio":"7.30%","count":"34.05","money":"614.60"},{"stock_code":"002179","stock_name":"中航光电","fund_code":"970033","fund_name":"东海海睿进取","ratio":"7.18%","count":"15.48","money":"603.84"},{"stock_code":"002557","stock_name":"洽洽食品","fund_code":"970033","fund_name":"东海海睿进取","ratio":"6.22%","count":"15.02","money":"523.00"},{"stock_code":"300593","stock_name":"新雷能","fund_code":"970033","fund_name":"东海海睿进取","ratio":"5.92%","count":"33.74","money":"498.30"},{"stock_code":"600519","stock_name":"贵州茅台","fund_code":"970033","fund_name":"东海海睿进取","ratio":"4.96%","count":"0.24","money":"417.69"},{"stock_code":"000568","stock_name":"泸州老窖","fund_code":"970033","fund_name":"东海海睿进取","ratio":"4.95%","count":"2.32","money":"416.25"},{"stock_code":"600372","stock_name":"中航机载","fund_code":"970033","fund_name":"东海海睿进取","ratio":"4.26%","count":"27.21","money":"358.61"},{"stock_code":"300750","stock_name":"宁德时代","fund_code":"970033","fund_name":"东海海睿进取","ratio":"3.45%","count":"1.78","money":"289.95"},{"stock_code":"603998","stock_name":"方盛制药","fund_code":"970033","fund_name":"东海海睿进取","ratio":"3.26%","count":"25.04","money":"274.44"},{"stock_code":"300595","stock_name":"欧普康视","fund_code":"970033","fund_name":"东海海睿进取","ratio":"2.89%","count":"10.78","money":"243.41"},{"stock_code":"605338","stock_name":"巴比食品","fund_code":"970033","fund_name":"东海海睿进取","ratio":"2.23%","count":"8.72","money":"187.31"},{"stock_code":"688685","stock_name":"迈信林","fund_code":"970033","fund_name":"东海海睿进取","ratio":"1.76%","count":"4.98","money":"148.13"}]