[{"stock_code":"601899","stock_name":"紫金矿业","fund_code":"000567","fund_name":"广发聚祥灵活","ratio":"5.06%","count":"36.94","money":"621.33"},{"stock_code":"600938","stock_name":"中国海油","fund_code":"000567","fund_name":"广发聚祥灵活","ratio":"4.24%","count":"17.82","money":"520.88"},{"stock_code":"300394","stock_name":"天孚通信","fund_code":"000567","fund_name":"广发聚祥灵活","ratio":"3.35%","count":"2.72","money":"411.45"},{"stock_code":"601168","stock_name":"西部矿业","fund_code":"000567","fund_name":"广发聚祥灵活","ratio":"3.15%","count":"20.06","money":"386.96"},{"stock_code":"300308","stock_name":"中际旭创","fund_code":"000567","fund_name":"广发聚祥灵活","ratio":"3.14%","count":"2.46","money":"385.14"},{"stock_code":"300502","stock_name":"新易盛","fund_code":"000567","fund_name":"广发聚祥灵活","ratio":"2.64%","count":"4.85","money":"324.68"},{"stock_code":"600188","stock_name":"兖矿能源","fund_code":"000567","fund_name":"广发聚祥灵活","ratio":"2.60%","count":"13.44","money":"319.74"},{"stock_code":"002327","stock_name":"富安娜","fund_code":"000567","fund_name":"广发聚祥灵活","ratio":"2.41%","count":"27.49","money":"296.34"},{"stock_code":"002463","stock_name":"沪电股份","fund_code":"000567","fund_name":"广发聚祥灵活","ratio":"2.31%","count":"9.40","money":"283.69"},{"stock_code":"601600","stock_name":"中国铝业","fund_code":"000567","fund_name":"广发聚祥灵活","ratio":"2.16%","count":"35.77","money":"264.70"}]