[{"stock_code":"300416","stock_name":"苏试试验","fund_code":"004608","fund_name":"长信乐信灵活","ratio":"2.20%","count":"4.60","money":"99.15"},{"stock_code":"600325","stock_name":"华发股份","fund_code":"004608","fund_name":"长信乐信灵活","ratio":"2.12%","count":"9.70","money":"95.55"},{"stock_code":"600685","stock_name":"中船防务","fund_code":"004608","fund_name":"长信乐信灵活","ratio":"2.03%","count":"3.05","money":"91.35"},{"stock_code":"603801","stock_name":"志邦家居","fund_code":"004608","fund_name":"长信乐信灵活","ratio":"2.02%","count":"2.76","money":"91.14"},{"stock_code":"002436","stock_name":"兴森科技","fund_code":"004608","fund_name":"长信乐信灵活","ratio":"1.99%","count":"5.79","money":"89.75"},{"stock_code":"601965","stock_name":"中国汽研","fund_code":"004608","fund_name":"长信乐信灵活","ratio":"1.99%","count":"4.34","money":"89.62"},{"stock_code":"600426","stock_name":"华鲁恒升","fund_code":"004608","fund_name":"长信乐信灵活","ratio":"1.97%","count":"2.90","money":"88.83"},{"stock_code":"000858","stock_name":"五粮液","fund_code":"004608","fund_name":"长信乐信灵活","ratio":"1.96%","count":"0.54","money":"88.33"},{"stock_code":"600519","stock_name":"贵州茅台","fund_code":"004608","fund_name":"长信乐信灵活","ratio":"1.88%","count":"0.05","money":"84.55"},{"stock_code":"300911","stock_name":"亿田智能","fund_code":"004608","fund_name":"长信乐信灵活","ratio":"1.74%","count":"2.06","money":"78.22"},{"stock_code":"002867","stock_name":"周大生","fund_code":"004608","fund_name":"长信乐信灵活","ratio":"1.69%","count":"4.29","money":"76.28"},{"stock_code":"688639","stock_name":"华恒生物","fund_code":"004608","fund_name":"长信乐信灵活","ratio":"1.68%","count":"0.84","money":"75.70"},{"stock_code":"688239","stock_name":"航宇科技","fund_code":"004608","fund_name":"长信乐信灵活","ratio":"1.62%","count":"1.04","money":"72.99"},{"stock_code":"688016","stock_name":"心脉医疗","fund_code":"004608","fund_name":"长信乐信灵活","ratio":"1.61%","count":"0.40","money":"72.49"},{"stock_code":"002648","stock_name":"卫星化学","fund_code":"004608","fund_name":"长信乐信灵活","ratio":"1.53%","count":"4.60","money":"68.82"},{"stock_code":"600975","stock_name":"新五丰","fund_code":"004608","fund_name":"长信乐信灵活","ratio":"1.49%","count":"7.02","money":"67.11"},{"stock_code":"688326","stock_name":"经纬恒润","fund_code":"004608","fund_name":"长信乐信灵活","ratio":"1.36%","count":"0.42","money":"61.25"},{"stock_code":"603076","stock_name":"乐惠国际","fund_code":"004608","fund_name":"长信乐信灵活","ratio":"1.20%","count":"1.13","money":"54.03"},{"stock_code":"300573","stock_name":"兴齐眼药","fund_code":"004608","fund_name":"长信乐信灵活","ratio":"1.19%","count":"0.25","money":"53.45"},{"stock_code":"000333","stock_name":"美的集团","fund_code":"004608","fund_name":"长信乐信灵活","ratio":"0.98%","count":"0.75","money":"44.19"}]