[{"stock_code":"300750","stock_name":"宁德时代","fund_code":"010242","fund_name":"平安稳健增长","ratio":"0.98%","count":"12.41","money":"2360.19"},{"stock_code":"002475","stock_name":"立讯精密","fund_code":"010242","fund_name":"平安稳健增长","ratio":"0.93%","count":"76.36","money":"2245.75"},{"stock_code":"002142","stock_name":"宁波银行","fund_code":"010242","fund_name":"平安稳健增长","ratio":"0.91%","count":"106.46","money":"2196.27"},{"stock_code":"601899","stock_name":"紫金矿业","fund_code":"010242","fund_name":"平安稳健增长","ratio":"0.79%","count":"113.26","money":"1904.95"},{"stock_code":"00700","stock_name":"腾讯控股","fund_code":"010242","fund_name":"平安稳健增长","ratio":"0.58%","count":"5.11","money":"1407.34"},{"stock_code":"000039","stock_name":"中集集团","fund_code":"010242","fund_name":"平安稳健增长","ratio":"0.57%","count":"144.42","money":"1382.10"},{"stock_code":"002984","stock_name":"森麒麟","fund_code":"010242","fund_name":"平安稳健增长","ratio":"0.57%","count":"44.01","money":"1380.02"},{"stock_code":"002050","stock_name":"三花智控","fund_code":"010242","fund_name":"平安稳健增长","ratio":"0.52%","count":"52.77","money":"1252.23"},{"stock_code":"600346","stock_name":"恒力石化","fund_code":"010242","fund_name":"平安稳健增长","ratio":"0.51%","count":"89.11","money":"1243.08"},{"stock_code":"000625","stock_name":"长安汽车","fund_code":"010242","fund_name":"平安稳健增长","ratio":"0.50%","count":"72.53","money":"1218.50"}]