[{"stock_code":"688169","stock_name":"石头科技","fund_code":"011196","fund_name":"摩根优势成长","ratio":"8.10%","count":"3.92","money":"1343.53"},{"stock_code":"601689","stock_name":"拓普集团","fund_code":"011196","fund_name":"摩根优势成长","ratio":"6.89%","count":"18.08","money":"1142.76"},{"stock_code":"300394","stock_name":"天孚通信","fund_code":"011196","fund_name":"摩根优势成长","ratio":"5.29%","count":"5.80","money":"877.52"},{"stock_code":"601138","stock_name":"工业富联","fund_code":"011196","fund_name":"摩根优势成长","ratio":"4.95%","count":"36.08","money":"821.53"},{"stock_code":"300308","stock_name":"中际旭创","fund_code":"011196","fund_name":"摩根优势成长","ratio":"4.54%","count":"4.81","money":"753.74"},{"stock_code":"002050","stock_name":"三花智控","fund_code":"011196","fund_name":"摩根优势成长","ratio":"4.32%","count":"30.17","money":"716.03"},{"stock_code":"000625","stock_name":"长安汽车","fund_code":"011196","fund_name":"摩根优势成长","ratio":"3.05%","count":"30.13","money":"506.18"},{"stock_code":"300750","stock_name":"宁德时代","fund_code":"011196","fund_name":"摩根优势成长","ratio":"2.85%","count":"2.48","money":"472.19"},{"stock_code":"300502","stock_name":"新易盛","fund_code":"011196","fund_name":"摩根优势成长","ratio":"2.74%","count":"6.78","money":"454.15"},{"stock_code":"002517","stock_name":"恺英网络","fund_code":"011196","fund_name":"摩根优势成长","ratio":"2.73%","count":"41.06","money":"452.53"}]