[{"stock_code":"600519","stock_name":"贵州茅台","fund_code":"011177","fund_name":"博时汇融回报","ratio":"5.90%","count":"5.11","money":"8701.82"},{"stock_code":"000568","stock_name":"泸州老窖","fund_code":"011177","fund_name":"博时汇融回报","ratio":"4.53%","count":"36.20","money":"6682.16"},{"stock_code":"000596","stock_name":"古井贡酒","fund_code":"011177","fund_name":"博时汇融回报","ratio":"3.96%","count":"22.47","money":"5842.88"},{"stock_code":"601225","stock_name":"陕西煤业","fund_code":"011177","fund_name":"博时汇融回报","ratio":"3.80%","count":"223.59","money":"5609.89"},{"stock_code":"600612","stock_name":"老凤祥","fund_code":"011177","fund_name":"博时汇融回报","ratio":"3.24%","count":"55.84","money":"4775.44"},{"stock_code":"300251","stock_name":"光线传媒","fund_code":"011177","fund_name":"博时汇融回报","ratio":"3.17%","count":"438.68","money":"4685.10"},{"stock_code":"601595","stock_name":"上海电影","fund_code":"011177","fund_name":"博时汇融回报","ratio":"2.70%","count":"132.67","money":"3980.10"},{"stock_code":"002739","stock_name":"万达电影","fund_code":"011177","fund_name":"博时汇融回报","ratio":"2.70%","count":"260.26","money":"3979.38"},{"stock_code":"002832","stock_name":"比音勒芬","fund_code":"011177","fund_name":"博时汇融回报","ratio":"2.60%","count":"131.69","money":"3843.91"},{"stock_code":"002327","stock_name":"富安娜","fund_code":"011177","fund_name":"博时汇融回报","ratio":"2.55%","count":"349.46","money":"3767.18"},{"stock_code":"600189","stock_name":"泉阳泉","fund_code":"011177","fund_name":"博时汇融回报","ratio":"1.99%","count":"321.21","money":"2932.65"},{"stock_code":"301262","stock_name":"海看股份","fund_code":"011177","fund_name":"博时汇融回报","ratio":"0.63%","count":"31.90","money":"930.84"}]