[{"stock_code":"000977","stock_name":"浪潮信息","fund_code":"011351","fund_name":"金鹰年年邮益","ratio":"2.47%","count":"8.50","money":"364.65"},{"stock_code":"300260","stock_name":"新莱应材","fund_code":"011351","fund_name":"金鹰年年邮益","ratio":"2.09%","count":"11.20","money":"309.79"},{"stock_code":"688596","stock_name":"正帆科技","fund_code":"011351","fund_name":"金鹰年年邮益","ratio":"1.78%","count":"6.90","money":"262.75"},{"stock_code":"002971","stock_name":"和远气体","fund_code":"011351","fund_name":"金鹰年年邮益","ratio":"1.64%","count":"9.00","money":"243.09"},{"stock_code":"688279","stock_name":"峰岹科技","fund_code":"011351","fund_name":"金鹰年年邮益","ratio":"1.54%","count":"2.00","money":"227.42"},{"stock_code":"688072","stock_name":"拓荆科技","fund_code":"011351","fund_name":"金鹰年年邮益","ratio":"1.37%","count":"1.08","money":"202.84"},{"stock_code":"688062","stock_name":"迈威生物","fund_code":"011351","fund_name":"金鹰年年邮益","ratio":"1.35%","count":"5.70","money":"199.61"},{"stock_code":"603002","stock_name":"宏昌电子","fund_code":"011351","fund_name":"金鹰年年邮益","ratio":"1.32%","count":"35.00","money":"195.65"},{"stock_code":"603890","stock_name":"春秋电子","fund_code":"011351","fund_name":"金鹰年年邮益","ratio":"1.31%","count":"21.00","money":"194.04"},{"stock_code":"000628","stock_name":"高新发展","fund_code":"011351","fund_name":"金鹰年年邮益","ratio":"1.29%","count":"2.50","money":"190.15"}]