[{"stock_code":"600150","stock_name":"中国船舶","fund_code":"012391","fund_name":"中欧产业前瞻","ratio":"9.26%","count":"340.00","money":"12580.00"},{"stock_code":"688012","stock_name":"中微公司","fund_code":"012391","fund_name":"中欧产业前瞻","ratio":"8.79%","count":"80.00","money":"11944.00"},{"stock_code":"600685","stock_name":"中船防务","fund_code":"012391","fund_name":"中欧产业前瞻","ratio":"8.61%","count":"450.01","money":"11695.66"},{"stock_code":"601989","stock_name":"中国重工","fund_code":"012391","fund_name":"中欧产业前瞻","ratio":"7.55%","count":"2,200.00","money":"10252.00"},{"stock_code":"600482","stock_name":"中国动力","fund_code":"012391","fund_name":"中欧产业前瞻","ratio":"5.83%","count":"390.00","money":"7913.10"},{"stock_code":"688120","stock_name":"华海清科","fund_code":"012391","fund_name":"中欧产业前瞻","ratio":"5.51%","count":"43.00","money":"7482.70"},{"stock_code":"688361","stock_name":"中科飞测","fund_code":"012391","fund_name":"中欧产业前瞻","ratio":"5.49%","count":"125.00","money":"7450.13"},{"stock_code":"688037","stock_name":"芯源微","fund_code":"012391","fund_name":"中欧产业前瞻","ratio":"5.43%","count":"66.01","money":"7374.41"},{"stock_code":"688072","stock_name":"拓荆科技","fund_code":"012391","fund_name":"中欧产业前瞻","ratio":"5.41%","count":"39.01","money":"7353.76"},{"stock_code":"002371","stock_name":"北方华创","fund_code":"012391","fund_name":"中欧产业前瞻","ratio":"4.50%","count":"20.00","money":"6112.00"}]