[{"stock_code":"300750","stock_name":"宁德时代","fund_code":"016117","fund_name":"贝莱德先进制","ratio":"7.34%","count":"9.50","money":"1806.06"},{"stock_code":"300308","stock_name":"中际旭创","fund_code":"016117","fund_name":"贝莱德先进制","ratio":"6.89%","count":"10.82","money":"1693.98"},{"stock_code":"002475","stock_name":"立讯精密","fund_code":"016117","fund_name":"贝莱德先进制","ratio":"6.01%","count":"50.21","money":"1476.68"},{"stock_code":"600660","stock_name":"福耀玻璃","fund_code":"016117","fund_name":"贝莱德先进制","ratio":"5.19%","count":"29.52","money":"1277.04"},{"stock_code":"300502","stock_name":"新易盛","fund_code":"016117","fund_name":"贝莱德先进制","ratio":"4.84%","count":"17.75","money":"1189.25"},{"stock_code":"00522","stock_name":"ASMPT","fund_code":"016117","fund_name":"贝莱德先进制","ratio":"4.76%","count":"13.13","money":"1171.26"},{"stock_code":"300394","stock_name":"天孚通信","fund_code":"016117","fund_name":"贝莱德先进制","ratio":"4.76%","count":"7.73","money":"1169.32"},{"stock_code":"688200","stock_name":"华峰测控","fund_code":"016117","fund_name":"贝莱德先进制","ratio":"4.72%","count":"11.14","money":"1160.81"},{"stock_code":"00700","stock_name":"腾讯控股","fund_code":"016117","fund_name":"贝莱德先进制","ratio":"3.82%","count":"3.41","money":"939.15"},{"stock_code":"688036","stock_name":"传音控股","fund_code":"016117","fund_name":"贝莱德先进制","ratio":"3.55%","count":"5.19","money":"872.53"}]