[{"stock_code":"600585","stock_name":"海螺水泥","fund_code":"017541","fund_name":"安信稳健增益","ratio":"0.80%","count":"12.04","money":"268.25"},{"stock_code":"601318","stock_name":"中国平安","fund_code":"017541","fund_name":"安信稳健增益","ratio":"0.70%","count":"5.76","money":"235.07"},{"stock_code":"000333","stock_name":"美的集团","fund_code":"017541","fund_name":"安信稳健增益","ratio":"0.63%","count":"3.31","money":"212.57"},{"stock_code":"300750","stock_name":"宁德时代","fund_code":"017541","fund_name":"安信稳健增益","ratio":"0.44%","count":"0.78","money":"148.32"},{"stock_code":"600036","stock_name":"招商银行","fund_code":"017541","fund_name":"安信稳健增益","ratio":"0.40%","count":"4.16","money":"133.95"},{"stock_code":"00688","stock_name":"中国海外发展","fund_code":"017541","fund_name":"安信稳健增益","ratio":"0.37%","count":"12.20","money":"124.53"},{"stock_code":"001979","stock_name":"招商蛇口","fund_code":"017541","fund_name":"安信稳健增益","ratio":"0.29%","count":"10.15","money":"95.92"},{"stock_code":"002466","stock_name":"天齐锂业","fund_code":"017541","fund_name":"安信稳健增益","ratio":"0.26%","count":"1.79","money":"85.87"},{"stock_code":"00288","stock_name":"万洲国际","fund_code":"017541","fund_name":"安信稳健增益","ratio":"0.25%","count":"17.80","money":"83.26"},{"stock_code":"00883","stock_name":"中国海洋石油","fund_code":"017541","fund_name":"安信稳健增益","ratio":"0.24%","count":"5.00","money":"82.13"}]